CHANGES.txt
LICENSE.txt
MANIFEST.in
README.rst
setup.py
django_hermes.egg-info/PKG-INFO
django_hermes.egg-info/SOURCES.txt
django_hermes.egg-info/dependency_links.txt
django_hermes.egg-info/top_level.txt
hermes/__init__.py
hermes/admin.py
hermes/feeds.py
hermes/models.py
hermes/renderers.py
hermes/settings.py
hermes/urls.py
hermes/views.py
hermes/migrations/0001_initial.py
hermes/migrations/0002_auto_20141101_1246.py
hermes/migrations/0003_post_is_published.py
hermes/migrations/0004_auto_20150819_2229.py
hermes/migrations/__init__.py
hermes/south_migrations/0001_initial.py
hermes/south_migrations/0002_auto__add_field_post_summary.py
hermes/south_migrations/0003_auto__add_category.py
hermes/south_migrations/0004_auto__chg_field_category_parent.py
hermes/south_migrations/0005_auto__add_field_post_category.py
hermes/south_migrations/0006_auto__add_field_post_hero.py
hermes/south_migrations/0007_auto__add_field_category_slug.py
hermes/south_migrations/0008_fill_slug_field.py
hermes/south_migrations/0009_auto__chg_field_post_hero__chg_field_category_slug.py
hermes/south_migrations/__init__.py
hermes/tests/__init__.py
hermes/tests/test_category_model.py
hermes/tests/test_feed.py
hermes/tests/test_post_model.py
hermes/tests/test_renderers.py
hermes/tests/test_views.py