Metadata-Version: 1.1
Name: django-hermes
Version: 1.4.2
Summary: A light-weight blogging app for Django.
Home-page: https://github.com/bunchesofdonald/django-hermes
Author: Chris Pickett
Author-email: chris.pickett@gmail.com
License: MIT
Platform: UNKNOWN
Classifier: Development Status :: 5 - Production/Stable
Classifier: Environment :: Web Environment
Classifier: Intended Audience :: Developers
Classifier: License :: OSI Approved :: MIT License
Classifier: Operating System :: OS Independent
Classifier: Programming Language :: Python
Classifier: Programming Language :: Python :: 2
Classifier: Programming Language :: Python :: 3
Classifier: Framework :: Django
Classifier: Natural Language :: English
Classifier: Topic :: Internet :: WWW/HTTP :: Dynamic Content :: News/Diary
